pycocotools/cocoeval.py
pycocotools/mask.py
pycocotools/_mask.cpython-311-x86_64-linux-gnu.so
pycocotools/coco.py
pycocotools/__init__.py
ocrd_fork_pycocotools-2.0.8.dist-info/top_level.txt
ocrd_fork_pycocotools-2.0.8.dist-info/METADATA
ocrd_fork_pycocotools-2.0.8.dist-info/RECORD
ocrd_fork_pycocotools-2.0.8.dist-info/WHEEL
