Metadata-Version: 2.4
Name: ocrd-fork-pycocotools
Version: 2.0.8
Summary: Official APIs for the MS-COCO dataset
Home-page: https://github.com/ppwwyyxx/cocoapi
License: FreeBSD
Requires-Python: >=3.8
Requires-Dist: matplotlib>=2.1.0
Requires-Dist: numpy
Dynamic: description
Dynamic: description-content-type
Dynamic: home-page
Dynamic: license
Dynamic: requires-dist
Dynamic: requires-python
Dynamic: summary
